neuroiatools/__init__.py
neuroiatools/version.py
neuroiatools/DisplayData/__init__.py
neuroiatools/DisplayData/plotEEG.py
neuroiatools/EEGManager/RawArray.py
neuroiatools/EEGManager/TrialsHandler.py
neuroiatools/EEGManager/__init__.py
neuroiatools/SignalProcessor/Filter.py
neuroiatools/SignalProcessor/ICA.py
neuroiatools/SignalProcessor/__init__.py
neuroiatools/SignalProcessor/tfr.py
neuroiatools/utils/__init__.py
neuroiatools/utils/datasetManager.py
neuroiatools/utils/montage_manager.py
neuroiatools-1.4.1.dist-info/METADATA
neuroiatools-1.4.1.dist-info/WHEEL
neuroiatools-1.4.1.dist-info/license.txt
neuroiatools-1.4.1.dist-info/top_level.txt
neuroiatools-1.4.1.dist-info/RECORD
